{"Routes":[{"SwaggerKey":"Achievements","DownstreamPathTemplate":"/Achievements","UpstreamPathTemplate":"/Achievements","UpstreamHttpMethod":["GET"],"DownstreamHttpMethod":null,"AddHeadersToRequest":{},"UpstreamHeaderTransform":{},"DownstreamHeaderTransform":{},"AddClaimsToRequest":{},"RouteClaimsRequirement":{},"AddQueriesToRequest":{},"ChangeDownstreamPathTemplate":{},"RequestIdKey":null,"FileCacheOptions":{"TtlSeconds":0,"Region":null},"RouteIsCaseSensitive":false,"ServiceName":null,"ServiceNamespace":null,"DownstreamScheme":"http","QoSOptions":{"ExceptionsAllowedBeforeBreaking":0,"DurationOfBreak":0,"TimeoutValue":0},"LoadBalancerOptions":{"Type":null,"Key":null,"Expiry":0},"RateLimitOptions":{"ClientWhitelist":[],"EnableRateLimiting":false,"Period":null,"PeriodTimespan":0.0,"Limit":0},"AuthenticationOptions":{"AuthenticationProviderKey":null,"AllowedScopes":[]},"HttpHandlerOptions":{"AllowAutoRedirect":false,"UseCookieContainer":false,"UseTracing":false,"UseProxy":true,"MaxConnectionsPerServer":2147483647},"DownstreamHostAndPorts":[{"Host":"localhost","Port":9999}],"UpstreamHost":null,"Key":null,"DelegatingHandlers":[],"Priority":1,"Timeout":0,"DangerousAcceptAnyServerCertificateValidator":false,"SecurityOptions":{"IPAllowedList":[],"IPBlockedList":[]},"DownstreamHttpVersion":null},{"SwaggerKey":"Achievements","DownstreamPathTemplate":"/Achievements/{everything}","UpstreamPathTemplate":"/Achievements/{everything}","UpstreamHttpMethod":["GET","POST","DELETE","PUT"],"DownstreamHttpMethod":null,"AddHeadersToRequest":{},"UpstreamHeaderTransform":{},"DownstreamHeaderTransform":{},"AddClaimsToRequest":{},"RouteClaimsRequirement":{},"AddQueriesToRequest":{},"ChangeDownstreamPathTemplate":{},"RequestIdKey":null,"FileCacheOptions":{"TtlSeconds":0,"Region":null},"RouteIsCaseSensitive":false,"ServiceName":null,"ServiceNamespace":null,"DownstreamScheme":"http","QoSOptions":{"ExceptionsAllowedBeforeBreaking":0,"DurationOfBreak":0,"TimeoutValue":0},"LoadBalancerOptions":{"Type":null,"Key":null,"Expiry":0},"RateLimitOptions":{"ClientWhitelist":[],"EnableRateLimiting":false,"Period":null,"PeriodTimespan":0.0,"Limit":0},"AuthenticationOptions":{"AuthenticationProviderKey":null,"AllowedScopes":[]},"HttpHandlerOptions":{"AllowAutoRedirect":false,"UseCookieContainer":false,"UseTracing":false,"UseProxy":true,"MaxConnectionsPerServer":2147483647},"DownstreamHostAndPorts":[{"Host":"localhost","Port":9999}],"UpstreamHost":null,"Key":null,"DelegatingHandlers":[],"Priority":1,"Timeout":0,"DangerousAcceptAnyServerCertificateValidator":false,"SecurityOptions":{"IPAllowedList":[],"IPBlockedList":[]},"DownstreamHttpVersion":null},{"SwaggerKey":"Authentication","DownstreamPathTemplate":"/Authentication","UpstreamPathTemplate":"/Authentication","UpstreamHttpMethod":["GET"],"DownstreamHttpMethod":null,"AddHeadersToRequest":{},"UpstreamHeaderTransform":{},"DownstreamHeaderTransform":{},"AddClaimsToRequest":{},"RouteClaimsRequirement":{},"AddQueriesToRequest":{},"ChangeDownstreamPathTemplate":{},"RequestIdKey":null,"FileCacheOptions":{"TtlSeconds":0,"Region":null},"RouteIsCaseSensitive":false,"ServiceName":null,"ServiceNamespace":null,"DownstreamScheme":"http","QoSOptions":{"ExceptionsAllowedBeforeBreaking":0,"DurationOfBreak":0,"TimeoutValue":0},"LoadBalancerOptions":{"Type":null,"Key":null,"Expiry":0},"RateLimitOptions":{"ClientWhitelist":[],"EnableRateLimiting":false,"Period":null,"PeriodTimespan":0.0,"Limit":0},"AuthenticationOptions":{"AuthenticationProviderKey":null,"AllowedScopes":[]},"HttpHandlerOptions":{"AllowAutoRedirect":false,"UseCookieContainer":false,"UseTracing":false,"UseProxy":true,"MaxConnectionsPerServer":2147483647},"DownstreamHostAndPorts":[{"Host":"localhost","Port":9999}],"UpstreamHost":null,"Key":null,"DelegatingHandlers":[],"Priority":1,"Timeout":0,"DangerousAcceptAnyServerCertificateValidator":false,"SecurityOptions":{"IPAllowedList":[],"IPBlockedList":[]},"DownstreamHttpVersion":null},{"SwaggerKey":"Authentication","DownstreamPathTemplate":"/Authentication/{everything}","UpstreamPathTemplate":"/Authentication/{everything}","UpstreamHttpMethod":["GET","POST","DELETE","PUT"],"DownstreamHttpMethod":null,"AddHeadersToRequest":{},"UpstreamHeaderTransform":{},"DownstreamHeaderTransform":{},"AddClaimsToRequest":{},"RouteClaimsRequirement":{},"AddQueriesToRequest":{},"ChangeDownstreamPathTemplate":{},"RequestIdKey":null,"FileCacheOptions":{"TtlSeconds":0,"Region":null},"RouteIsCaseSensitive":false,"ServiceName":null,"ServiceNamespace":null,"DownstreamScheme":"http","QoSOptions":{"ExceptionsAllowedBeforeBreaking":0,"DurationOfBreak":0,"TimeoutValue":0},"LoadBalancerOptions":{"Type":null,"Key":null,"Expiry":0},"RateLimitOptions":{"ClientWhitelist":[],"EnableRateLimiting":false,"Period":null,"PeriodTimespan":0.0,"Limit":0},"AuthenticationOptions":{"AuthenticationProviderKey":null,"AllowedScopes":[]},"HttpHandlerOptions":{"AllowAutoRedirect":false,"UseCookieContainer":false,"UseTracing":false,"UseProxy":true,"MaxConnectionsPerServer":2147483647},"DownstreamHostAndPorts":[{"Host":"localhost","Port":9999}],"UpstreamHost":null,"Key":null,"DelegatingHandlers":[],"Priority":1,"Timeout":0,"DangerousAcceptAnyServerCertificateValidator":false,"SecurityOptions":{"IPAllowedList":[],"IPBlockedList":[]},"DownstreamHttpVersion":null},{"SwaggerKey":"Blog","DownstreamPathTemplate":"/Blog","UpstreamPathTemplate":"/Blog","UpstreamHttpMethod":["GET"],"DownstreamHttpMethod":null,"AddHeadersToRequest":{},"UpstreamHeaderTransform":{},"DownstreamHeaderTransform":{},"AddClaimsToRequest":{},"RouteClaimsRequirement":{},"AddQueriesToRequest":{},"ChangeDownstreamPathTemplate":{},"RequestIdKey":null,"FileCacheOptions":{"TtlSeconds":0,"Region":null},"RouteIsCaseSensitive":false,"ServiceName":null,"ServiceNamespace":null,"DownstreamScheme":"http","QoSOptions":{"ExceptionsAllowedBeforeBreaking":0,"DurationOfBreak":0,"TimeoutValue":0},"LoadBalancerOptions":{"Type":null,"Key":null,"Expiry":0},"RateLimitOptions":{"ClientWhitelist":[],"EnableRateLimiting":false,"Period":null,"PeriodTimespan":0.0,"Limit":0},"AuthenticationOptions":{"AuthenticationProviderKey":null,"AllowedScopes":[]},"HttpHandlerOptions":{"AllowAutoRedirect":false,"UseCookieContainer":false,"UseTracing":false,"UseProxy":true,"MaxConnectionsPerServer":2147483647},"DownstreamHostAndPorts":[{"Host":"localhost","Port":9999}],"UpstreamHost":null,"Key":null,"DelegatingHandlers":[],"Priority":1,"Timeout":0,"DangerousAcceptAnyServerCertificateValidator":false,"SecurityOptions":{"IPAllowedList":[],"IPBlockedList":[]},"DownstreamHttpVersion":null},{"SwaggerKey":"Blog","DownstreamPathTemplate":"/Blog/{everything}","UpstreamPathTemplate":"/Blog/{everything}","UpstreamHttpMethod":["GET","POST","DELETE","PUT"],"DownstreamHttpMethod":null,"AddHeadersToRequest":{},"UpstreamHeaderTransform":{},"DownstreamHeaderTransform":{},"AddClaimsToRequest":{},"RouteClaimsRequirement":{},"AddQueriesToRequest":{},"ChangeDownstreamPathTemplate":{},"RequestIdKey":null,"FileCacheOptions":{"TtlSeconds":0,"Region":null},"RouteIsCaseSensitive":false,"ServiceName":null,"ServiceNamespace":null,"DownstreamScheme":"http","QoSOptions":{"ExceptionsAllowedBeforeBreaking":0,"DurationOfBreak":0,"TimeoutValue":0},"LoadBalancerOptions":{"Type":null,"Key":null,"Expiry":0},"RateLimitOptions":{"ClientWhitelist":[],"EnableRateLimiting":false,"Period":null,"PeriodTimespan":0.0,"Limit":0},"AuthenticationOptions":{"AuthenticationProviderKey":null,"AllowedScopes":[]},"HttpHandlerOptions":{"AllowAutoRedirect":false,"UseCookieContainer":false,"UseTracing":false,"UseProxy":true,"MaxConnectionsPerServer":2147483647},"DownstreamHostAndPorts":[{"Host":"localhost","Port":9999}],"UpstreamHost":null,"Key":null,"DelegatingHandlers":[],"Priority":1,"Timeout":0,"DangerousAcceptAnyServerCertificateValidator":false,"SecurityOptions":{"IPAllowedList":[],"IPBlockedList":[]},"DownstreamHttpVersion":null},{"SwaggerKey":"Comments","DownstreamPathTemplate":"/Comments","UpstreamPathTemplate":"/Comments","UpstreamHttpMethod":["GET"],"DownstreamHttpMethod":null,"AddHeadersToRequest":{},"UpstreamHeaderTransform":{},"DownstreamHeaderTransform":{},"AddClaimsToRequest":{},"RouteClaimsRequirement":{},"AddQueriesToRequest":{},"ChangeDownstreamPathTemplate":{},"RequestIdKey":null,"FileCacheOptions":{"TtlSeconds":0,"Region":null},"RouteIsCaseSensitive":false,"ServiceName":null,"ServiceNamespace":null,"DownstreamScheme":"http","QoSOptions":{"ExceptionsAllowedBeforeBreaking":0,"DurationOfBreak":0,"TimeoutValue":0},"LoadBalancerOptions":{"Type":null,"Key":null,"Expiry":0},"RateLimitOptions":{"ClientWhitelist":[],"EnableRateLimiting":false,"Period":null,"PeriodTimespan":0.0,"Limit":0},"AuthenticationOptions":{"AuthenticationProviderKey":null,"AllowedScopes":[]},"HttpHandlerOptions":{"AllowAutoRedirect":false,"UseCookieContainer":false,"UseTracing":false,"UseProxy":true,"MaxConnectionsPerServer":2147483647},"DownstreamHostAndPorts":[{"Host":"localhost","Port":9999}],"UpstreamHost":null,"Key":null,"DelegatingHandlers":[],"Priority":1,"Timeout":0,"DangerousAcceptAnyServerCertificateValidator":false,"SecurityOptions":{"IPAllowedList":[],"IPBlockedList":[]},"DownstreamHttpVersion":null},{"SwaggerKey":"Comments","DownstreamPathTemplate":"/Comments/{everything}","UpstreamPathTemplate":"/Comments/{everything}","UpstreamHttpMethod":["GET","POST","DELETE","PUT"],"DownstreamHttpMethod":null,"AddHeadersToRequest":{},"UpstreamHeaderTransform":{},"DownstreamHeaderTransform":{},"AddClaimsToRequest":{},"RouteClaimsRequirement":{},"AddQueriesToRequest":{},"ChangeDownstreamPathTemplate":{},"RequestIdKey":null,"FileCacheOptions":{"TtlSeconds":0,"Region":null},"RouteIsCaseSensitive":false,"ServiceName":null,"ServiceNamespace":null,"DownstreamScheme":"http","QoSOptions":{"ExceptionsAllowedBeforeBreaking":0,"DurationOfBreak":0,"TimeoutValue":0},"LoadBalancerOptions":{"Type":null,"Key":null,"Expiry":0},"RateLimitOptions":{"ClientWhitelist":[],"EnableRateLimiting":false,"Period":null,"PeriodTimespan":0.0,"Limit":0},"AuthenticationOptions":{"AuthenticationProviderKey":null,"AllowedScopes":[]},"HttpHandlerOptions":{"AllowAutoRedirect":false,"UseCookieContainer":false,"UseTracing":false,"UseProxy":true,"MaxConnectionsPerServer":2147483647},"DownstreamHostAndPorts":[{"Host":"localhost","Port":9999}],"UpstreamHost":null,"Key":null,"DelegatingHandlers":[],"Priority":1,"Timeout":0,"DangerousAcceptAnyServerCertificateValidator":false,"SecurityOptions":{"IPAllowedList":[],"IPBlockedList":[]},"DownstreamHttpVersion":null},{"SwaggerKey":"Followers","DownstreamPathTemplate":"/Followers","UpstreamPathTemplate":"/Followers","UpstreamHttpMethod":["GET"],"DownstreamHttpMethod":null,"AddHeadersToRequest":{},"UpstreamHeaderTransform":{},"DownstreamHeaderTransform":{},"AddClaimsToRequest":{},"RouteClaimsRequirement":{},"AddQueriesToRequest":{},"ChangeDownstreamPathTemplate":{},"RequestIdKey":null,"FileCacheOptions":{"TtlSeconds":0,"Region":null},"RouteIsCaseSensitive":false,"ServiceName":null,"ServiceNamespace":null,"DownstreamScheme":"http","QoSOptions":{"ExceptionsAllowedBeforeBreaking":0,"DurationOfBreak":0,"TimeoutValue":0},"LoadBalancerOptions":{"Type":null,"Key":null,"Expiry":0},"RateLimitOptions":{"ClientWhitelist":[],"EnableRateLimiting":false,"Period":null,"PeriodTimespan":0.0,"Limit":0},"AuthenticationOptions":{"AuthenticationProviderKey":null,"AllowedScopes":[]},"HttpHandlerOptions":{"AllowAutoRedirect":false,"UseCookieContainer":false,"UseTracing":false,"UseProxy":true,"MaxConnectionsPerServer":2147483647},"DownstreamHostAndPorts":[{"Host":"localhost","Port":9999}],"UpstreamHost":null,"Key":null,"DelegatingHandlers":[],"Priority":1,"Timeout":0,"DangerousAcceptAnyServerCertificateValidator":false,"SecurityOptions":{"IPAllowedList":[],"IPBlockedList":[]},"DownstreamHttpVersion":null},{"SwaggerKey":"Followers","DownstreamPathTemplate":"/Followers/{everything}","UpstreamPathTemplate":"/Followers/{everything}","UpstreamHttpMethod":["GET","POST","DELETE","PUT"],"DownstreamHttpMethod":null,"AddHeadersToRequest":{},"UpstreamHeaderTransform":{},"DownstreamHeaderTransform":{},"AddClaimsToRequest":{},"RouteClaimsRequirement":{},"AddQueriesToRequest":{},"ChangeDownstreamPathTemplate":{},"RequestIdKey":null,"FileCacheOptions":{"TtlSeconds":0,"Region":null},"RouteIsCaseSensitive":false,"ServiceName":null,"ServiceNamespace":null,"DownstreamScheme":"http","QoSOptions":{"ExceptionsAllowedBeforeBreaking":0,"DurationOfBreak":0,"TimeoutValue":0},"LoadBalancerOptions":{"Type":null,"Key":null,"Expiry":0},"RateLimitOptions":{"ClientWhitelist":[],"EnableRateLimiting":false,"Period":null,"PeriodTimespan":0.0,"Limit":0},"AuthenticationOptions":{"AuthenticationProviderKey":null,"AllowedScopes":[]},"HttpHandlerOptions":{"AllowAutoRedirect":false,"UseCookieContainer":false,"UseTracing":false,"UseProxy":true,"MaxConnectionsPerServer":2147483647},"DownstreamHostAndPorts":[{"Host":"localhost","Port":9999}],"UpstreamHost":null,"Key":null,"DelegatingHandlers":[],"Priority":1,"Timeout":0,"DangerousAcceptAnyServerCertificateValidator":false,"SecurityOptions":{"IPAllowedList":[],"IPBlockedList":[]},"DownstreamHttpVersion":null},{"SwaggerKey":"Solutions","DownstreamPathTemplate":"/Solutions","UpstreamPathTemplate":"/Solutions","UpstreamHttpMethod":["GET"],"DownstreamHttpMethod":null,"AddHeadersToRequest":{},"UpstreamHeaderTransform":{},"DownstreamHeaderTransform":{},"AddClaimsToRequest":{},"RouteClaimsRequirement":{},"AddQueriesToRequest":{},"ChangeDownstreamPathTemplate":{},"RequestIdKey":null,"FileCacheOptions":{"TtlSeconds":0,"Region":null},"RouteIsCaseSensitive":false,"ServiceName":null,"ServiceNamespace":null,"DownstreamScheme":"http","QoSOptions":{"ExceptionsAllowedBeforeBreaking":0,"DurationOfBreak":0,"TimeoutValue":0},"LoadBalancerOptions":{"Type":null,"Key":null,"Expiry":0},"RateLimitOptions":{"ClientWhitelist":[],"EnableRateLimiting":false,"Period":null,"PeriodTimespan":0.0,"Limit":0},"AuthenticationOptions":{"AuthenticationProviderKey":null,"AllowedScopes":[]},"HttpHandlerOptions":{"AllowAutoRedirect":false,"UseCookieContainer":false,"UseTracing":false,"UseProxy":true,"MaxConnectionsPerServer":2147483647},"DownstreamHostAndPorts":[{"Host":"localhost","Port":5005}],"UpstreamHost":null,"Key":null,"DelegatingHandlers":[],"Priority":1,"Timeout":0,"DangerousAcceptAnyServerCertificateValidator":false,"SecurityOptions":{"IPAllowedList":[],"IPBlockedList":[]},"DownstreamHttpVersion":null},{"SwaggerKey":"Solutions","DownstreamPathTemplate":"/Solutions/{everything}","UpstreamPathTemplate":"/Solution/{everything}","UpstreamHttpMethod":["GET","POST","DELETE","PUT"],"DownstreamHttpMethod":null,"AddHeadersToRequest":{},"UpstreamHeaderTransform":{},"DownstreamHeaderTransform":{},"AddClaimsToRequest":{},"RouteClaimsRequirement":{},"AddQueriesToRequest":{},"ChangeDownstreamPathTemplate":{},"RequestIdKey":null,"FileCacheOptions":{"TtlSeconds":0,"Region":null},"RouteIsCaseSensitive":false,"ServiceName":null,"ServiceNamespace":null,"DownstreamScheme":"http","QoSOptions":{"ExceptionsAllowedBeforeBreaking":0,"DurationOfBreak":0,"TimeoutValue":0},"LoadBalancerOptions":{"Type":null,"Key":null,"Expiry":0},"RateLimitOptions":{"ClientWhitelist":[],"EnableRateLimiting":false,"Period":null,"PeriodTimespan":0.0,"Limit":0},"AuthenticationOptions":{"AuthenticationProviderKey":null,"AllowedScopes":[]},"HttpHandlerOptions":{"AllowAutoRedirect":false,"UseCookieContainer":false,"UseTracing":false,"UseProxy":true,"MaxConnectionsPerServer":2147483647},"DownstreamHostAndPorts":[{"Host":"localhost","Port":5005}],"UpstreamHost":null,"Key":null,"DelegatingHandlers":[],"Priority":1,"Timeout":0,"DangerousAcceptAnyServerCertificateValidator":false,"SecurityOptions":{"IPAllowedList":[],"IPBlockedList":[]},"DownstreamHttpVersion":null},{"SwaggerKey":"Users","DownstreamPathTemplate":"/Users","UpstreamPathTemplate":"/Users","UpstreamHttpMethod":["GET"],"DownstreamHttpMethod":null,"AddHeadersToRequest":{},"UpstreamHeaderTransform":{},"DownstreamHeaderTransform":{},"AddClaimsToRequest":{},"RouteClaimsRequirement":{},"AddQueriesToRequest":{},"ChangeDownstreamPathTemplate":{},"RequestIdKey":null,"FileCacheOptions":{"TtlSeconds":0,"Region":null},"RouteIsCaseSensitive":false,"ServiceName":null,"ServiceNamespace":null,"DownstreamScheme":"http","QoSOptions":{"ExceptionsAllowedBeforeBreaking":0,"DurationOfBreak":0,"TimeoutValue":0},"LoadBalancerOptions":{"Type":null,"Key":null,"Expiry":0},"RateLimitOptions":{"ClientWhitelist":[],"EnableRateLimiting":false,"Period":null,"PeriodTimespan":0.0,"Limit":0},"AuthenticationOptions":{"AuthenticationProviderKey":null,"AllowedScopes":[]},"HttpHandlerOptions":{"AllowAutoRedirect":false,"UseCookieContainer":false,"UseTracing":false,"UseProxy":true,"MaxConnectionsPerServer":2147483647},"DownstreamHostAndPorts":[{"Host":"localhost","Port":9999}],"UpstreamHost":null,"Key":null,"DelegatingHandlers":[],"Priority":1,"Timeout":0,"DangerousAcceptAnyServerCertificateValidator":false,"SecurityOptions":{"IPAllowedList":[],"IPBlockedList":[]},"DownstreamHttpVersion":null},{"SwaggerKey":"Users","DownstreamPathTemplate":"/Users/{everything}","UpstreamPathTemplate":"/Users/{everything}","UpstreamHttpMethod":["GET","POST","DELETE","PUT"],"DownstreamHttpMethod":null,"AddHeadersToRequest":{},"UpstreamHeaderTransform":{},"DownstreamHeaderTransform":{},"AddClaimsToRequest":{},"RouteClaimsRequirement":{},"AddQueriesToRequest":{},"ChangeDownstreamPathTemplate":{},"RequestIdKey":null,"FileCacheOptions":{"TtlSeconds":0,"Region":null},"RouteIsCaseSensitive":false,"ServiceName":null,"ServiceNamespace":null,"DownstreamScheme":"http","QoSOptions":{"ExceptionsAllowedBeforeBreaking":0,"DurationOfBreak":0,"TimeoutValue":0},"LoadBalancerOptions":{"Type":null,"Key":null,"Expiry":0},"RateLimitOptions":{"ClientWhitelist":[],"EnableRateLimiting":false,"Period":null,"PeriodTimespan":0.0,"Limit":0},"AuthenticationOptions":{"AuthenticationProviderKey":null,"AllowedScopes":[]},"HttpHandlerOptions":{"AllowAutoRedirect":false,"UseCookieContainer":false,"UseTracing":false,"UseProxy":true,"MaxConnectionsPerServer":2147483647},"DownstreamHostAndPorts":[{"Host":"localhost","Port":9999}],"UpstreamHost":null,"Key":null,"DelegatingHandlers":[],"Priority":1,"Timeout":0,"DangerousAcceptAnyServerCertificateValidator":false,"SecurityOptions":{"IPAllowedList":[],"IPBlockedList":[]},"DownstreamHttpVersion":null}],"DynamicRoutes":[],"Aggregates":[],"GlobalConfiguration":{"RequestIdKey":null,"ServiceDiscoveryProvider":{"Scheme":null,"Host":null,"Port":0,"Type":null,"Token":null,"ConfigurationKey":null,"PollingInterval":0,"Namespace":null},"RateLimitOptions":{"ClientIdHeader":"ClientId","QuotaExceededMessage":null,"RateLimitCounterPrefix":"ocelot","DisableRateLimitHeaders":false,"HttpStatusCode":429},"QoSOptions":{"ExceptionsAllowedBeforeBreaking":0,"DurationOfBreak":0,"TimeoutValue":0},"BaseUrl":null,"LoadBalancerOptions":{"Type":null,"Key":null,"Expiry":0},"DownstreamScheme":null,"HttpHandlerOptions":{"AllowAutoRedirect":false,"UseCookieContainer":false,"UseTracing":false,"UseProxy":true,"MaxConnectionsPerServer":2147483647},"DownstreamHttpVersion":null},"SwaggerEndPoints":[{"Key":"Solutions","VersionPlaceholder":"{version}","KeyToPath":"Solutions","Config":[{"Name":"Solution API","Version":"v1","Url":"http://localhost:5005/swagger/v1/swagger.json","Service":null}],"HostOverride":null,"TransformByOcelotConfig":true,"TakeServersFromDownstreamService":false},{"Key":"Comments","VersionPlaceholder":"{version}","KeyToPath":"Comments","Config":[{"Name":"Comment API","Version":"v1","Url":"http://localhost:9999/swagger/v1/swagger.json","Service":null}],"HostOverride":null,"TransformByOcelotConfig":true,"TakeServersFromDownstreamService":false},{"Key":"Users","VersionPlaceholder":"{version}","KeyToPath":"Users","Config":[{"Name":"User API","Version":"v1","Url":"http://localhost:9999/swagger/v1/swagger.json","Service":null}],"HostOverride":null,"TransformByOcelotConfig":true,"TakeServersFromDownstreamService":false},{"Key":"Authentication","VersionPlaceholder":"{version}","KeyToPath":"Authentication","Config":[{"Name":"Authentication API","Version":"v1","Url":"http://localhost:9999/swagger/v1/swagger.json","Service":null}],"HostOverride":null,"TransformByOcelotConfig":true,"TakeServersFromDownstreamService":false},{"Key":"Blog","VersionPlaceholder":"{version}","KeyToPath":"Blog","Config":[{"Name":"Blog API","Version":"v1","Url":"http://localhost:9999/swagger/v1/swagger.json","Service":null}],"HostOverride":null,"TransformByOcelotConfig":true,"TakeServersFromDownstreamService":false},{"Key":"Followers","VersionPlaceholder":"{version}","KeyToPath":"Followers","Config":[{"Name":"Follower API","Version":"v1","Url":"http://localhost:9999/swagger/v1/swagger.json","Service":null}],"HostOverride":null,"TransformByOcelotConfig":true,"TakeServersFromDownstreamService":false},{"Key":"Achievements","VersionPlaceholder":"{version}","KeyToPath":"Achievements","Config":[{"Name":"Achievement API","Version":"v1","Url":"http://localhost:9999/swagger/v1/swagger.json","Service":null}],"HostOverride":null,"TransformByOcelotConfig":true,"TakeServersFromDownstreamService":false}]}